aria2jrpc/__init__.py
aria2jrpc/aria2.py
aria2jrpc/models.py
aria2jrpc-0.0.2.dist-info/LICENCE
aria2jrpc-0.0.2.dist-info/METADATA
aria2jrpc-0.0.2.dist-info/WHEEL
aria2jrpc-0.0.2.dist-info/top_level.txt
aria2jrpc-0.0.2.dist-info/RECORD
