Metadata-Version: 2.1
Name: aria2jrpc
Version: 0.0.2
Summary: A small package to help you work with aria2 jrpc
Author-email: SeyedMohammadAli Noori <13noori79@gmail.com>
Project-URL: Homepage, https://github.com/alinri/aria2jrpc
Project-URL: Bug Tracker, https://github.com/alinri/aria2jrpc/issues
Classifier: Programming Language :: Python :: 3
Classifier: License :: OSI Approved :: MIT License
Classifier: Operating System :: OS Independent
Requires-Python: >=3.7
License-File: LICENCE
Requires-Dist: requests
